whispy/__init__.py
whispy/__main__.py
whispy/cli.py
whispy/realtime.py
whispy/recorder.py
whispy/transcribe.py
whisper_py-0.1.0.dist-info/METADATA
whisper_py-0.1.0.dist-info/WHEEL
whisper_py-0.1.0.dist-info/entry_points.txt
whisper_py-0.1.0.dist-info/top_level.txt
whisper_py-0.1.0.dist-info/zip-safe
whisper_py-0.1.0.dist-info/RECORD
